sqlink/__init__.py
sqlink/dao.py
sqlink/database.py
sqlink/entity.py
sqlink-1.6.1.dist-info/LICENSE.txt
sqlink-1.6.1.dist-info/METADATA
sqlink-1.6.1.dist-info/WHEEL
sqlink-1.6.1.dist-info/top_level.txt
sqlink-1.6.1.dist-info/RECORD
