Metadata-Version: 2.1
Name: sqlink
Version: 1.6.1
Summary: a efficient and concise sql framework.
Home-page: https://gitee.com/darlingxyz/sqlink
Author: NanHaiLoong
Author-email: nanhai@163.com
License: UNKNOWN
Platform: UNKNOWN
Classifier: Programming Language :: Python :: 3
Classifier: License :: OSI Approved :: MIT License
Classifier: Operating System :: OS Independent
License-File: LICENSE.txt
